{
  "atualizadoEm": "2026-06-17T11:49:22Z",
  "mesReferencia": "2026-06",
  "tipo": "corrente",
  "taxa_usd": 5.078,
  "fonte_usd": "BCB 16/06/2026",
  "gastos": {
    "aux-moradia": {
      "google": 0.0,
      "meta": 10751.73,
      "leads_novos": 246,
      "ganhos": 15,
      "valor_ganhos": 48570.6,
      "orcamento_diario_google": 60.0,
      "orcamento_diario_meta": 823.28,
      "orcamento_diario": 883.28
    },
    "fies": {
      "google": 0.0,
      "meta": 13618.52,
      "leads_novos": 222,
      "ganhos": 12,
      "valor_ganhos": 44389.0,
      "orcamento_diario_google": 0.0,
      "orcamento_diario_meta": 807.43,
      "orcamento_diario": 807.43
    },
    "fies-suspensao": {
      "google": 0.0,
      "meta": 1455.95,
      "leads_novos": 3,
      "ganhos": 2,
      "valor_ganhos": 3781.0,
      "orcamento_diario_google": 0.0,
      "orcamento_diario_meta": 90.0,
      "orcamento_diario": 90.0
    },
    "direito-medico": {
      "google": 0.0,
      "meta": 323.87,
      "leads_novos": 20,
      "ganhos": 3,
      "valor_ganhos": 10470.0,
      "orcamento_diario_google": 0.0,
      "orcamento_diario_meta": 50.0,
      "orcamento_diario": 50.0
    },
    "inss": {
      "google": 0.0,
      "meta": 407.31,
      "leads_novos": 9,
      "ganhos": 3,
      "valor_ganhos": 5680.0,
      "orcamento_diario_google": 0.0,
      "orcamento_diario_meta": 24.0,
      "orcamento_diario": 24.0
    },
    "provab": {
      "google": 0.0,
      "meta": 103.15,
      "leads_novos": 6,
      "ganhos": 1,
      "valor_ganhos": 2241.0,
      "orcamento_diario_google": 0.0,
      "orcamento_diario_meta": 6.0,
      "orcamento_diario": 6.0
    },
    "seguro": {
      "google": 15942.64,
      "meta": 0.0,
      "leads_novos": 313,
      "ganhos": 29,
      "valor_ganhos": 76823.04,
      "orcamento_diario_google": 820.0,
      "orcamento_diario_meta": 0.0,
      "orcamento_diario": 820.0
    },
    "livre-ir": {
      "google": 0.0,
      "meta": 0.0,
      "leads_novos": 20,
      "ganhos": 0,
      "valor_ganhos": 0.0,
      "orcamento_diario_google": 0.0,
      "orcamento_diario_meta": 0.0,
      "orcamento_diario": 0.0
    },
    "seg-vida": {
      "google": 2141.62,
      "meta": 975.19,
      "leads_novos": 27,
      "ganhos": 1,
      "valor_ganhos": 1990.0,
      "orcamento_diario_google": 203.0,
      "orcamento_diario_meta": 60.0,
      "orcamento_diario": 263.0
    }
  }
}